BusServoControl/BusServoControl.py
BusServoControl/__init__.py
BusServoControl-1.0.dist-info/METADATA
BusServoControl-1.0.dist-info/WHEEL
BusServoControl-1.0.dist-info/top_level.txt
BusServoControl-1.0.dist-info/RECORD
