Metadata-Version: 2.1
Name: BusServoControl
Version: 1.0
Summary: A module for controlling servo motors
Home-page: https://github.com/LeurDeLis/BusServoControl
Author: Ma Fukang
Author-email: 956787367@qq.com
License: MIT
Platform: UNKNOWN
